setup.py
asterisk/__init__.py
asterisk/ai.py
asterisk/wikidata.py
asterisk.egg-info/PKG-INFO
asterisk.egg-info/SOURCES.txt
asterisk.egg-info/dependency_links.txt
asterisk.egg-info/not-zip-safe
asterisk.egg-info/requires.txt
asterisk.egg-info/top_level.txt