Metadata-Version: 1.0
Name: asterisk
Version: 0.0.8
Summary: Tools for computing asset risk with respect to goals.
Home-page: https://github.com/mindey/asterisk
Author: Mindey I.
Author-email: mindey@qq.com
License: MIT
Platform: UNKNOWN
